pdfixsdk/Pdfix.py
pdfixsdk/__init__.py
pdfixsdk/bin/aarch64/libpdf.so
pdfixsdk/bin/arm64/libpdf.dylib
pdfixsdk/bin/x86_64/LicenseSpringVMD.dll
pdfixsdk/bin/x86_64/libpdf.dylib
pdfixsdk/bin/x86_64/libpdf.so
pdfixsdk/bin/x86_64/pdf.dll
pdfix_sdk-8.7.10.dist-info/METADATA
pdfix_sdk-8.7.10.dist-info/WHEEL
pdfix_sdk-8.7.10.dist-info/top_level.txt
pdfix_sdk-8.7.10.dist-info/RECORD
