Metadata-Version: 2.4
Name: pdfix-sdk
Version: 8.7.10
Summary: PDFix SDK - Automated PDF Remediation, Data Extraction, HTML Conversion
Home-page: https://github.com/pdfix/pdfix-sdk-pypi-package
Author: PDFix s.r.o.
Author-email: support@pdfix.net
Project-URL: Documentation, https://github.com/pdfix/pdfix-sdk-pypi-package
Project-URL: Bug Reports, https://github.com/pdfix/pdfix-sdk-pypi-package/issues
Project-URL: Source Code, https://github.com/pdfix/pdfix-sdk-pypi-package
Project-URL: Homepage, https://pdfix.net
Project-URL: License, https://pdfix.net/terms
Keywords: pdfix,pdf,accessibility,remediation,extraction,html,conversion,render,watermark,redact,sign,forms
Classifier: Development Status :: 5 - Production/Stable
Classifier: Intended Audience :: Developers
Classifier: Topic :: Software Development :: Build Tools
Classifier: Programming Language :: Python :: 3
Classifier: Programming Language :: Python :: 3.6
Classifier: Programming Language :: Python :: 3.7
Classifier: Programming Language :: Python :: 3.8
Classifier: Programming Language :: Python :: 3.9
Classifier: Programming Language :: Python :: 3 :: Only
Classifier: License :: Other/Proprietary License
Classifier: Operating System :: OS Independent
Requires-Python: >=3.7
Requires-Dist: requests
Provides-Extra: dev
Requires-Dist: check-manifest; extra == "dev"
Dynamic: author
Dynamic: author-email
Dynamic: classifier
Dynamic: description
Dynamic: description-content-type
Dynamic: home-page
Dynamic: keywords
Dynamic: project-url
Dynamic: provides-extra
Dynamic: requires-dist
Dynamic: requires-python
Dynamic: summary
